<po>
	<message msgid="man apply" msgstr="Apply" />
	<message msgid="man cancel" msgstr="Cancel" />
	<message msgid="man bSAVE" msgstr="Save" />   
	<message msgid="man onbutton" msgstr="Enable" />
	<message msgid="man offbutton" msgstr="Disable" />
	<message msgid="help" msgstr="Help" />
	<message msgid="toplanguage" msgstr="e" />
	<message msgid="settingwaiting" msgstr="Setting,Please Wait......" />

	<message msgid="man ntp title" msgstr="Time settings" />
	<message msgid="man ntp des" msgstr="Manually or automatically set the system time" />
	<message msgid="man ntp setting" msgstr="Time Settings" />
	<message msgid="man ntp timezone" msgstr="Time Zone" />
	<message msgid="man ntp mid island" msgstr="(GMT-11:00) Midway Island, Samoa" />
	<message msgid="man ntp hawaii" msgstr="(GMT-10:00) Hawaii" />
	<message msgid="man ntp alaska" msgstr="(GMT-09:00) Alaska" />
	<message msgid="man ntp pacific" msgstr="(GMT-08:00) Pacific Time" />
	<message msgid="man ntp mountain" msgstr="(GMT-07:00) Mountain Time" />

	<message msgid="man ntp arizona" msgstr="(GMT-07:00) Arizona" />
	<message msgid="man ntp central" msgstr="(GMT-06:00) Central Time" />
	<message msgid="man ntp mid us" msgstr="(GMT-06:00) Middle America" />
	<message msgid="man ntp indiana east" msgstr="(GMT-05:00) Indiana East, Colombia" />
	<message msgid="man ntp eastern" msgstr="(GMT-05:00) Eastern Time" />
	<message msgid="man ntp atlantic" msgstr="(GMT-04:00) Atlantic Time, Brazil West" />
	<message msgid="man ntp bolivia" msgstr="(GMT-04:00) Bolivia, Venezuela" />
	<message msgid="man ntp guyana" msgstr="(GMT-03:00) Guyana" />
	<message msgid="man ntp brazil east" msgstr="(GMT-03:00) Brazil East, Greenland" />
	<message msgid="man ntp mid atlantic" msgstr="(GMT-02:00) Mid-Atlantic" />
	<message msgid="man ntp azores islands" msgstr="(GMT-01:00) Azores Islands" />
	<message msgid="man ntp gambia" msgstr="(GMT) Gambia, Liberia, Morocco" />
	<message msgid="man ntp england" msgstr="(GMT) England" />
	<message msgid="man ntp czech republic" msgstr="(GMT+01:00) Czech Republic" />
	<message msgid="man ntp germany" msgstr="(GMT+01:00) Germany" />
	<message msgid="man ntp tunisia" msgstr="(GMT+01:00) Tunisia" />
	<message msgid="man ntp greece" msgstr="(GMT+02:00) Greece, Ukraine, Turkey" />
	<message msgid="man ntp south africa" msgstr="(GMT+02:00) South Africa" />
	<message msgid="man ntp iraq" msgstr="(GMT+03:00) Iraq, Jordan, Kuwait" />
	<message msgid="man ntp moscow winter" msgstr="(GMT+03:00) Moscow Winter Time" />
	<message msgid="man ntp armenia" msgstr="(GMT+04:00) Armenia" />
	<message msgid="man ntp pakistan" msgstr="(GMT+05:00) Pakistan, Russia" />
	<message msgid="man ntp bangladesh" msgstr="(GMT+06:00) Bangladesh, Russia" />
	<message msgid="man ntp thailand" msgstr="(GMT+07:00) Thailand, Russia" />
	<message msgid="man ntp chinacoast" msgstr="(GMT+08:00) China Coast, Hong Kong" />
	<message msgid="man ntp taipei" msgstr="(GMT+08:00) Taipei" />
	<message msgid="man ntp singapore" msgstr="(GMT+08:00) Singapore" />
	<message msgid="man ntp australia wa" msgstr="(GMT+08:00) Australia (WA)" />
	<message msgid="man ntp japan" msgstr="(GMT+09:00) Japan, Korea" />
	<message msgid="man ntp korean" msgstr="(GMT+09:00) Korean" />
	<message msgid="man ntp guam" msgstr="(GMT+10:00) Guam, Russia" />
	<message msgid="man ntp australia qld" msgstr="(GMT+10:00) Australia (QLD, TAS,NSW,ACT,VIC)" />
	<message msgid="man ntp solomon islands" msgstr="(GMT+11:00) Solomon Islands" />
	<message msgid="man ntp fiji" msgstr="(GMT+12:00) Fiji" />
	<message msgid="man ntp newzealand" msgstr="(GMT+12:00) New Zealand" />

	<message msgid="man ntp server1" msgstr="First choice of NTP server" />
	<message msgid="man ntp server2" msgstr="Alternative NTP Server" />
	<message msgid="man ntp tzs" msgstr="Connection status" />
	<message msgid="man ntp current time" msgstr="Current Time" />
	<message msgid="man ntp sync with host" msgstr="Sync with host" />
	<message msgid="man ntpswitch" msgstr="NTP Automatic synchronization" />
	<message msgid="ntp waring" msgstr="Note: close the router to power, the system time information will be lost, only to start the automatic synchronization network time server function, the next time you boot connected to the Internet, the router will automatically time operation, or require you to manually set up time. Time setting accuracy, other functions (such as access control) in the time limit to take effect." />
	
	<message msgid="man ntp err1" msgstr="Please specify a NTP Server." />
	<message msgid="man ntp servererror" msgstr="Network time server address is wrong, please fill in the correct format IP or domain name" />
	
	<message msgid="man cfgdes" msgstr="The configuration file export, import and system backup and recovery" />
	<message msgid="man export" msgstr="Export configuration" />
	<message msgid="man exporttitle" msgstr="Configure management" />
	<message msgid="man exportdes" msgstr="The system configuration files are saved to the local." />
	<message msgid="man selsectfile" msgstr="Select the configuration file" />
	<message msgid="man inportdes" msgstr="To make local system configuration file work in the BASE" /> 
	<message msgid="man inport" msgstr="Inport configuration" />
	<message msgid="man localsave" msgstr="Internal backup" />
	<message msgid="man cfg backup" msgstr="Are you sure you want to use this profile?" />
	<message msgid="err cfg empty" msgstr="Please select the need to import the configuration file" />
	<message msgid="err cfg format" msgstr="Configuration file is illegal" />
	<message msgid="err cfg upload" msgstr="Configuration file import fail" />
	<message msgid="man cfg backto1" msgstr="Are you sure to back to" />
	<message msgid="man cfg backto2" msgstr="?" />
	<message msgid="man cfg backupdel1" msgstr="Are you sure to delete" />	
	<message msgid="man cfg backupdel2" msgstr=" backup will be delete" />
	<message msgid="err cfg full" msgstr="Backup space is full, please delete some backups" />

	<message msgid="err cfg big" msgstr="Configuration file should smaller than 1M" />	
	
	

	<message msgid="cfg care1" msgstr="Note:" />	
	<message msgid="cfg care2" msgstr="1.The configuration file should less than 1M.Import configuration files, equipment in the user configuration will be lost. If you load the configuration file is wrong, may cause the equipment cannot work." />	
	<message msgid="cfg care3" msgstr="2.Import configuration file process cannot be shut off the power supply of the HBD router, otherwise it will cause damage to the router and can not be used. The import process about 20 seconds, the import after the completion of HBD routing will automatically restart." />	

	
	<message msgid="man reboottitle" msgstr="System restart" />
	<message msgid="man rebootdes" msgstr="Restart BASE" />
	<message msgid="man reboot" msgstr="Restart" />

	<message msgid="man basesavedes" msgstr="BASE Backup and Restore" />
	<message msgid="man basesavetitle" msgstr="BASE Backup" />
	<message msgid="man basesavetitle2" msgstr="BASE Restore" />
	<message msgid="man date" msgstr="Date" />
	<message msgid="man modify" msgstr="Delete" />

	<message msgid="log title" msgstr="System Log" />
	<message msgid="log des" msgstr="Display system log" />
	<message msgid="log t1des" msgstr="Display system log" />
	<message msgid="log exportlog"	msgstr="Display log" />
	
	<message msgid="log t2des" msgstr="Tcpdump" />
	<message msgid="log begin" msgstr="Begin" />
	<message msgid="log end" msgstr="End" />
	<message msgid="log export" msgstr="Export" />

	<message msgid="man use" msgstr="USE" />
	<message msgid="man delete" msgstr="DELETE" />
	<message msgid="err MAC wuxiao" msgstr="MAC address is illegal" />
	<message msgid="err MAC empty" msgstr="MAC is empty " />
	<message msgid="err user empty" msgstr="User name is empty " />
	<message msgid="err pwd empty" msgstr="Password is empty " />
	<message msgid="err time empty" msgstr="Time is empty " />

	<message msgid="err MAC format" msgstr="MAC address is illegal,Please input as XX:XX:XX:XX:XX:XX (X is hexadecimal digit)" />
	<message msgid="err format" msgstr="Parameter is illegal " />
	<message msgid="err range" msgstr="Parameter range error " />
	<message msgid="man chfile" msgstr="Choose file" />
	<message msgid="man sysreboot" msgstr="Confirm restart BASE?" />
	<message msgid="err IP empty" msgstr="IP address can not be empty" />
	<message msgid="err sub empty" msgstr="Subnet can not be empty" />
	<message msgid="err gw empty" msgstr="Gateway can not be empty" />
	<message msgid="err DNS empty" msgstr="DNS can not be empty" />
	<message msgid="err IP format" msgstr="IP address is illegal" />
	<message msgid="err sub format" msgstr="Subnet address is illegal" />	
	<message msgid="err gw format" msgstr="Gateway address is illegal" />
	<message msgid="err DNS format" msgstr="DNS address is illegal" />
</po>